contextstore/__init__.py
contextstore/interfaces.py
contextstore/memory_backends.py
contextstore-0.1.0.dist-info/licenses/LICENSE
contextstore-0.1.0.dist-info/METADATA
contextstore-0.1.0.dist-info/WHEEL
contextstore-0.1.0.dist-info/top_level.txt
contextstore-0.1.0.dist-info/RECORD
