Metadata-Version: 2.4
Name: contextstore
Version: 0.1.0
Summary: A generic package for persisting conversation history across different storage backends
Author-email: Your Name <your.email@example.com>
License: MIT
Project-URL: Homepage, https://github.com/yourusername/contextstore
Project-URL: Documentation, https://github.com/yourusername/contextstore#readme
Project-URL: Repository, https://github.com/yourusername/contextstore
Project-URL: Issues, https://github.com/yourusername/contextstore/issues
Keywords: conversation,history,memory,persistence,chat,llm
Classifier: Development Status :: 4 - Beta
Classifier: Intended Audience :: Developers
Classifier: License :: OSI Approved :: MIT License
Classifier: Programming Language :: Python :: 3
Classifier: Programming Language :: Python :: 3.8
Classifier: Programming Language :: Python :: 3.9
Classifier: Programming Language :: Python :: 3.10
Classifier: Programming Language :: Python :: 3.11
Classifier: Programming Language :: Python :: 3.12
Classifier: Topic :: Software Development :: Libraries :: Python Modules
Requires-Python: >=3.8
License-File: LICENSE
Dynamic: license-file
